consume_substrait/__init__.py
consume_substrait/consumers.py
produce_substrait/__init__.py
produce_substrait/java_definitions.py
produce_substrait/producers.py
produce_substrait/jars/isthmus-0.5.0-all.jar
substrait_tools-0.0.3.dist-info/METADATA
substrait_tools-0.0.3.dist-info/WHEEL
substrait_tools-0.0.3.dist-info/entry_points.txt
substrait_tools-0.0.3.dist-info/top_level.txt
substrait_tools-0.0.3.dist-info/RECORD
