Metadata-Version: 2.1
Name: substrait-tools
Version: 0.0.3
Summary: A Substrait command line tool
Author: richtia
Project-URL: Repository, https://github.com/richtia/substrait-tools
Requires-Python: >=3.9, <4
Requires-Dist: duckdb (>=0.6.2.dev1766)
Requires-Dist: filelock
Requires-Dist: ibis-framework
Requires-Dist: ibis-substrait
Requires-Dist: JPype1
Requires-Dist: protobuf
Requires-Dist: pyarrow
Requires-Dist: substrait-validator
